ec2pricing/__init__.py
ec2pricing/main.py
ec2pricing/version.py
aws_ec2_pricing-0.1.10.dist-info/entry_points.txt
aws_ec2_pricing-0.1.10.dist-info/LICENSE
aws_ec2_pricing-0.1.10.dist-info/WHEEL
aws_ec2_pricing-0.1.10.dist-info/METADATA
aws_ec2_pricing-0.1.10.dist-info/RECORD
