Metadata-Version: 2.1
Name: aws-ec2-pricing
Version: 0.1.10
Summary: CLI tool to build SQLite table from AWS EC2 prices.
Home-page: https://github.com/vduseev/aws-ec2-pricing
License: Apache-2.0
Keywords: aws,ec2,pricing,sql
Author: vduseev
Author-email: vagiz@duseev.com
Maintainer: vduseev
Maintainer-email: vagiz@duseev.com
Requires-Python: >=3.9,<4.0
Classifier: Development Status :: 4 - Beta
Classifier: Environment :: Console
Classifier: License :: OSI Approved :: Apache Software License
Classifier: Programming Language :: Python :: 3
Classifier: Programming Language :: Python :: 3.9
Requires-Dist: boto3 (>=1.18.40,<2.0.0)
Requires-Dist: click (>=8.0.1,<9.0.0)
Requires-Dist: prettytable (>=2.2.0,<3.0.0)
Project-URL: Documentation, https://github.com/vduseev/aws-ec2-pricing
Project-URL: Repository, https://github.com/vduseev/aws-ec2-pricing
